Workbook
Name Slicer_Agent_Assigned: #N/A
Name Slicer_Answered: #N/A
Name Slicer_Breached_SLA: #N/A
Name Slicer_Breached_SLA1: #N/A
Name Slicer_Current_Status: #N/A
Name Slicer_Department: #N/A
Name Slicer_Overdue: #N/A
Name Slicer_Priority: #N/A
Name Slicer_Source: #N/A
Name Slicer_Team_Assigned: #N/A
Name Slicer_Type: #N/A

Sheet helpdesk_tickets
A1: Ticket Number | B1: Date Created | C1: Subject | D1: From | E1: From Email | F1: Priority | G1: Department | H1: Type | I1: Source | J1: Current Status | K1: Last Updated | L1: Due Date | M1: Overdue | N1: Answered | O1: Agent Assigned | P1: Team Lead | Q1: Team Assigned | R1: Thread Count | S1: Attachment Count | T1: Category | U1: Issue Origin | V1: Select Ticket Status Update | W1: SLA Due Date | X1: Breached SLA | Y1: SR No. | Z1: Corrective Actions | AA1: Preventive Actions | AB1: Closed By
A2: 111636 | B2: 44267.415 | C2: Error Displaying In Different Module | D2: Jasper John | E2: jasper.john@gmail.com | F2: Emergency | G2: SAP JDE Support Department | H2: Incident / Problem | I2: Web | J2: Closed | K2: 44279.722 | L2: 44267.581 | M2: 0 | N2: 1 | O2: Jared Smith | P2: N/A | Q2: SAP Support Team | R2: 16 | S2: 2 | T2: PROD | U2: PRODUCTION | V2: New Ticket | W2: {=IF(H2="Request","No SLA for Request", IF(F2="Emergency",B2+(4/24), WORKDAY(B2, _xlfn.IFS(F2="High", 3, F2="Normal", 5, F2="Low", 10))))} -> 44267.581 | X2: =IF(K2>=W2,"Yes",IF(W2="No SLA for Request","N/A","No")) -> Yes
A3: 111632 | B3: 44265.681 | C3: Approval Workflow Error | D3: Erick White | E3: ewhite@yahoo.com | F3: Emergency | G3: SAP JDE Support Department | H3: Incident / Problem | I3: Web | J3: Resolved | K3: 44273.719 | L3: 44270.681 | M3: 1 | N3: 1 | O3: Mark Jikkins | P3: N/A | Q3: JDE Support Team | R3: 28 | S3: 6 | T3: PROD | U3: PRODUCTION | V3: New Ticket | W3: {=IF(H3="Request","No SLA for Request", IF(F3="Emergency",B3+(4/24), WORKDAY(B3, _xlfn.IFS(F3="High", 3, F3="Normal", 5, F3="Low", 10))))} -> 44265.848 | X3: =IF(K3>=W3,"Yes",IF(W3="No SLA for Request","N/A","No")) -> Yes
A4: 111621 | B4: 44249.506 | C4: Public Ip Trusted Certificate Authority Error | D4: Tomi Yamamoto | E4: tyamamoto@gmail.com | F4: Emergency | G4: InterN/Al Technical Department | H4: Incident / Problem | I4: Web | J4: Closed | K4: 44260.611 | L4: 44250.006 | M4: 0 | N4: 1 | O4: Jared Smith | P4: N/A | Q4: Network Team | R4: 5 | S4: 1 | T4: PROD | U4: PRODUCTION | V4: New Ticket | W4: {=IF(H4="Request","No SLA for Request", IF(F4="Emergency",B4+(4/24), WORKDAY(B4, _xlfn.IFS(F4="High", 3, F4="Normal", 5, F4="Low", 10))))} -> 44249.672 | X4: =IF(K4>=W4,"Yes",IF(W4="No SLA for Request","N/A","No")) -> Yes
A5: 111608 | B5: 44242.487 | C5: Jde Slowdown | D5: Riza Richardson | E5: rrichardson@mailiN/Ator.com | F5: Emergency | G5: SAP JDE Support Department | H5: Incident / Problem | I5: Web | J5: Closed | K5: 44251.736 | L5: 44242.987 | M5: 0 | N5: 1 | O5: Jared Smith | P5: N/A | Q5: JDE Support Team | R5: 12 | S5: 1 | T5: PROD | U5: PRODUCTION | V5: Close Ticket | W5: {=IF(H5="Request","No SLA for Request", IF(F5="Emergency",B5+(4/24), WORKDAY(B5, _xlfn.IFS(F5="High", 3, F5="Normal", 5, F5="Low", 10))))} -> 44242.653 | X5: =IF(K5>=W5,"Yes",IF(W5="No SLA for Request","N/A","No")) -> Yes
A6: 111596 | B6: 44218.457 | C6: Jde Slow Down | D6: Riza Richardson | E6: rrichardson@mailiN/Ator.com | F6: Emergency | G6: SAP JDE Support Department | H6: Incident / Problem | I6: Web | J6: Closed | K6: 44225.722 | L6: 44218.957 | M6: 0 | N6: 1 | O6: Jared Smith | P6: N/A | Q6: JDE Support Team | R6: 7 | S6: 1 | T6: PROD | U6: PRODUCTION | V6: Close Ticket | W6: {=IF(H6="Request","No SLA for Request", IF(F6="Emergency",B6+(4/24), WORKDAY(B6, _xlfn.IFS(F6="High", 3, F6="Normal", 5, F6="Low", 10))))} -> 44218.624 | X6: =IF(K6>=W6,"Yes",IF(W6="No SLA for Request","N/A","No")) -> Yes
A7: 111491 | B7: 44063.4 | C7: Error 504 Gateway Timeout Again | D7: Aurora Miller | E7: aurora.miller@outlook.com | F7: Emergency | G7: SAP JDE Support Department | H7: Incident / Problem | I7: Web | J7: Closed | K7: 44211.692 | L7: 44063.9 | M7: 0 | N7: 1 | O7: Jared Smith | P7: N/A | Q7: SAP Support Team | R7: 11 | S7: 1 | T7: PROD | U7: PRODUCTION | V7: Close Ticket | W7: {=IF(H7="Request","No SLA for Request", IF(F7="Emergency",B7+(4/24), WORKDAY(B7, _xlfn.IFS(F7="High", 3, F7="Normal", 5, F7="Low", 10))))} -> 44063.567 | X7: =IF(K7>=W7,"Yes",IF(W7="No SLA for Request","N/A","No")) -> Yes
A8: 111571 | B8: 44175.399 | C8: Login Issue | D8: Aurora Miller | E8: aurora.miller@outlook.com | F8: Emergency | G8: SAP JDE Support Department | H8: Incident / Problem | I8: Web | J8: Closed | K8: 44200.742 | L8: 44175.899 | M8: 0 | N8: 1 | O8: Jared Smith | P8: N/A | Q8: SAP Support Team | R8: 5 | S8: 4 | T8: PROD | U8: PRODUCTION | V8: Open | W8: {=IF(H8="Request","No SLA for Request", IF(F8="Emergency",B8+(4/24), WORKDAY(B8, _xlfn.IFS(F8="High", 3, F8="Normal", 5, F8="Low", 10))))} -> 44175.566 | X8: =IF(K8>=W8,"Yes",IF(W8="No SLA for Request","N/A","No")) -> Yes
A9: 111575 | B9: 44175.416 | C9: "Bea.Jolt" Login Error | D9: Aurora Miller | E9: aurora.miller@outlook.com | F9: Emergency | G9: SAP JDE Support Department | H9: Incident / Problem | I9: Web | J9: Closed | K9: 44200.74 | L9: 44175.916 | M9: 0 | N9: 1 | O9: Jared Smith | P9: N/A | Q9: SAP Support Team | R9: 5 | S9: 1 | T9: PROD | U9: PRODUCTION | V9: Open | W9: {=IF(H9="Request","No SLA for Request", IF(F9="Emergency",B9+(4/24), WORKDAY(B9, _xlfn.IFS(F9="High", 3, F9="Normal", 5, F9="Low", 10))))} -> 44175.583 | X9: =IF(K9>=W9,"Yes",IF(W9="No SLA for Request","N/A","No")) -> Yes
A10: 111576 | B10: 44175.419 | C10: Slow Performance | D10: Aurora Miller | E10: aurora.miller@outlook.com | F10: Emergency | G10: SAP JDE Support Department | H10: Incident / Problem | I10: Web | J10: Closed | K10: 44200.739 | L10: 44175.919 | M10: 0 | N10: 1 | O10: Jared Smith | P10: N/A | Q10: SAP Support Team | R10: 5 | S10: 1 | T10: PROD | U10: PRODUCTION | V10: Open | W10: {=IF(H10="Request","No SLA for Request", IF(F10="Emergency",B10+(4/24), WORKDAY(B10, _xlfn.IFS(F10="High", 3, F10="Normal", 5, F10="Low", 10))))} -> 44175.586 | X10: =IF(K10>=W10,"Yes",IF(W10="No SLA for Request","N/A","No")) -> Yes
A11: 111581 | B11: 44183.428 | C11: Hr Technical AN/Alyzer In Test | D11: Kian Rogers | E11: krogers@mailiN/Ator.com | F11: Emergency | G11: SAP JDE Support Department | H11: Request | I11: Web | J11: Closed | K11: 44200.501 | L11: 44183.928 | M11: 0 | N11: 1 | O11: Jared Smith | P11: N/A | Q11: JDE Support Team | R11: 9 | S11: 2 | T11: NON-PROD | U11: TEST | V11: Close Ticket | W11: {=IF(H11="Request","No SLA for Request", IF(F11="Emergency",B11+(4/24), WORKDAY(B11, _xlfn.IFS(F11="High", 3, F11="Normal", 5, F11="Low", 10))))} -> No SLA for Request | X11: =IF(K11>=W11,"Yes",IF(W11="No SLA for Request","N/A","No")) -> N/A
A12: 111586 | B12: 44188.637 | C12: Open Vpn Authenticator App Setup | D12: Kenex Willows | E12: kwillows@yahoo.com | F12: Emergency | G12: SAP JDE Support Department | H12: Request | I12: Web | J12: Closed | K12: 44193.734 | L12: 44189.137 | M12: 0 | N12: 1 | O12: Jared Smith | P12: N/A | Q12: JDE Support Team | R12: 7 | S12: 0 | T12: PROD | U12: PRODUCTION | V12: Close Ticket | W12: {=IF(H12="Request","No SLA for Request", IF(F12="Emergency",B12+(4/24), WORKDAY(B12, _xlfn.IFS(F12="High", 3, F12="Normal", 5, F12="Low", 10))))} -> No SLA for Request | X12: =IF(K12>=W12,"Yes",IF(W12="No SLA for Request","N/A","No")) -> N/A
A13: 111564 | B13: 44160.66 | C13: Login Issue | D13: Aurora Miller | E13: aurora.miller@outlook.com | F13: Emergency | G13: SAP JDE Support Department | H13: Incident / Problem | I13: Web | J13: Closed | K13: 44175.719 | L13: 44161.16 | M13: 0 | N13: 1 | O13: Stellar Murad | P13: N/A | Q13: SAP Support Team | R13: 5 | S13: 1 | T13: PROD | U13: PRODUCTION | V13: New Ticket | W13: {=IF(H13="Request","No SLA for Request", IF(F13="Emergency",B13+(4/24), WORKDAY(B13, _xlfn.IFS(F13="High", 3, F13="Normal", 5, F13="Low", 10))))} -> 44160.827 | X13: =IF(K13>=W13,"Yes",IF(W13="No SLA for Request","N/A","No")) -> Yes
... A20: 111451 | B20: 44013.383 | C20: Laptop Repair | D20: Monique Smiths | E20: msmiths@yahoo.com | F20: Emergency | G20: InterN/Al Technical Department | H20: Incident / Problem | I20: Phone | J20: Closed | K20: 44021.636 | L20: 44014.708 | M20: 0 | N20: 1 | O20: Jared Smith | P20: N/A | Q20: Network Team | R20: 4 | S20: 0 | T20: NON-PROD | U20: DEVELOPMENT | V20: New Ticket | W20: {=IF(H20="Request","No SLA for Request", IF(F20="Emergency",B20+(4/24), WORKDAY(B20, _xlfn.IFS(F20="High", 3, F20="Normal", 5, F20="Low", 10))))} -> 44013.55 | X20: =IF(K20>=W20,"Yes",IF(W20="No SLA for Request","N/A","No")) -> Yes
A21: 111430 | B21: 43984.435 | C21: Sap Not Accessible | D21: Aurora Miller | E21: aurora.miller@outlook.com | F21: Emergency | G21: SAP JDE Support Department | H21: Incident / Problem | I21: Web | J21: Closed | K21: 43998.741 | L21: N/A | M21: 0 | N21: 1 | O21: Jared Smith | P21: N/A | Q21: SAP Support Team | R21: 11 | S21: 2 | T21: PROD | U21: PRODUCTION | V21: Close Ticket | W21: {=IF(H21="Request","No SLA for Request", IF(F21="Emergency",B21+(4/24), WORKDAY(B21, _xlfn.IFS(F21="High", 3, F21="Normal", 5, F21="Low", 10))))} -> 43984.601 | X21: =IF(K21>=W21,"Yes",IF(W21="No SLA for Request","N/A","No")) -> Yes
A22: 111424 | B22: 43978.393 | C22: Sap Production Is Down | D22: Aurora Miller | E22: aurora.miller@outlook.com | F22: Emergency | G22: SAP JDE Support Department | H22: Incident / Problem | I22: Web | J22: Closed | K22: 43992.726 | L22: N/A | M22: 0 | N22: 1 | O22: Jared Smith | P22: N/A | Q22: SAP Support Team | R22: 12 | S22: 20 | T22: PROD | U22: PRODUCTION | V22: New Ticket | W22: {=IF(H22="Request","No SLA for Request", IF(F22="Emergency",B22+(4/24), WORKDAY(B22, _xlfn.IFS(F22="High", 3, F22="Normal", 5, F22="Low", 10))))} -> 43978.56 | X22: =IF(K22>=W22,"Yes",IF(W22="No SLA for Request","N/A","No")) -> Yes
A23: 111416 | B23: 43948.392 | C23: System Downtime | D23: Aurora Miller | E23: aurora.miller@outlook.com | F23: Emergency | G23: SAP JDE Support Department | H23: Incident / Problem | I23: Web | J23: Closed | K23: 43955.717 | L23: N/A | M23: 0 | N23: 1 | O23: Jared Smith | P23: N/A | Q23: SAP Support Team | R23: 5 | S23: 2 | T23: PROD | U23: PRODUCTION | V23: New Ticket | W23: {=IF(H23="Request","No SLA for Request", IF(F23="Emergency",B23+(4/24), WORKDAY(B23, _xlfn.IFS(F23="High", 3, F23="Normal", 5, F23="Low", 10))))} -> 43948.558 | X23: =IF(K23>=W23,"Yes",IF(W23="No SLA for Request","N/A","No")) -> Yes
A24: 111403 | B24: 43913.4 | C24: Prod: IN/Active Phase / Status: No MaN/Ager | D24: Melody Thompson | E24: mthompson@yahoo.com | F24: Emergency | G24: SAP JDE Support Department | H24: Incident / Problem | I24: Web | J24: Closed | K24: 43916.778 | L24: N/A | M24: 0 | N24: 1 | O24: Jared Smith | P24: N/A | Q24: JDE Support Team | R24: 7 | S24: 2 | T24: PROD | U24: DEVELOPMENT | V24: New Ticket | W24: {=IF(H24="Request","No SLA for Request", IF(F24="Emergency",B24+(4/24), WORKDAY(B24, _xlfn.IFS(F24="High", 3, F24="Normal", 5, F24="Low", 10))))} -> 43913.567 | X24: =IF(K24>=W24,"Yes",IF(W24="No SLA for Request","N/A","No")) -> Yes
A25: 111387 | B25: 43874.384 | C25: Prod: Slowdown Of Jde In Production Instance | D25: Melody Thompson | E25: mthompson@yahoo.com | F25: Emergency | G25: SAP JDE Support Department | H25: Incident / Problem | I25: Web | J25: Closed | K25: 43879.585 | L25: N/A | M25: 0 | N25: 1 | O25: Jared Smith | P25: N/A | Q25: JDE Support Team | R25: 10 | S25: 7 | T25: PROD | U25: DEVELOPMENT | V25: New Ticket | W25: {=IF(H25="Request","No SLA for Request", IF(F25="Emergency",B25+(4/24), WORKDAY(B25, _xlfn.IFS(F25="High", 3, F25="Normal", 5, F25="Low", 10))))} -> 43874.551 | X25: =IF(K25>=W25,"Yes",IF(W25="No SLA for Request","N/A","No")) -> Yes
A26: 111384 | B26: 43871.466 | C26: Sql Access MaN/Ager Sql Error | D26: Aurora Miller | E26: aurora.miller@outlook.com | F26: Emergency | G26: SAP JDE Support Department | H26: Incident / Problem | I26: Web | J26: Closed | K26: 43872.656 | L26: N/A | M26: 0 | N26: 1 | O26: Jared Smith | P26: N/A | Q26: AWS Team | R26: 5 | S26: 2 | T26: PROD | U26: PRODUCTION | V26: Close Ticket | W26: {=IF(H26="Request","No SLA for Request", IF(F26="Emergency",B26+(4/24), WORKDAY(B26, _xlfn.IFS(F26="High", 3, F26="Normal", 5, F26="Low", 10))))} -> 43871.633 | X26: =IF(K26>=W26,"Yes",IF(W26="No SLA for Request","N/A","No")) -> Yes
A27: 111366 | B27: 43833.585 | C27: Error On Finish Enrolling | D27: Marvin Peters | E27: mpeters@outlook.com | F27: Emergency | G27: SAP JDE Support Department | H27: Incident / Problem | I27: Web | J27: Closed | K27: 43844.733 | L27: N/A | M27: 0 | N27: 1 | O27: Jared Smith | P27: N/A | Q27: SAP Support Team | R27: 10 | S27: 2 | T27: PROD | U27: DEVELOPMENT | V27: New Ticket | W27: {=IF(H27="Request","No SLA for Request", IF(F27="Emergency",B27+(4/24), WORKDAY(B27, _xlfn.IFS(F27="High", 3, F27="Normal", 5, F27="Low", 10))))} -> 43833.751 | X27: =IF(K27>=W27,"Yes",IF(W27="No SLA for Request","N/A","No")) -> Yes
A28: 111364 | B28: 43833.456 | C28: Slow Loading In Sap | D28: Jasper John | E28: jasper.john@gmail.com | F28: Emergency | G28: SAP JDE Support Department | H28: Incident / Problem | I28: Web | J28: Closed | K28: 43840.749 | L28: N/A | M28: 0 | N28: 1 | O28: Jared Smith | P28: N/A | Q28: SAP Support Team | R28: 11 | S28: 4 | T28: PROD | U28: DEVELOPMENT | V28: New Ticket | W28: {=IF(H28="Request","No SLA for Request", IF(F28="Emergency",B28+(4/24), WORKDAY(B28, _xlfn.IFS(F28="High", 3, F28="Normal", 5, F28="Low", 10))))} -> 43833.623 | X28: =IF(K28>=W28,"Yes",IF(W28="No SLA for Request","N/A","No")) -> Yes
A29: 111357 | B29: 43809.625 | C29: Request For Reconfigure Of Palo Alto | D29: Tomi Yamamoto | E29: tyamamoto@gmail.com | F29: Emergency | G29: InterN/Al Technical Department | H29: Request | I29: Web | J29: Closed | K29: 43817.692 | L29: 43810.125 | M29: 0 | N29: 1 | O29: Stellar Murad | P29: N/A | Q29: Network Team | R29: 4 | S29: 0 | T29: N/A | U29: N/A | V29: New Ticket | W29: {=IF(H29="Request","No SLA for Request", IF(F29="Emergency",B29+(4/24), WORKDAY(B29, _xlfn.IFS(F29="High", 3, F29="Normal", 5, F29="Low", 10))))} -> No SLA for Request | X29: =IF(K29>=W29,"Yes",IF(W29="No SLA for Request","N/A","No")) -> N/A
A30: 111347 | B30: 43791.691 | C30: Sap Production Downtime Issue | D30: John Brown | E30: jbrown@outlook.com | F30: Emergency | G30: SAP JDE Support Department | H30: Incident / Problem | I30: Web | J30: Closed | K30: 43811.472 | L30: 43792.191 | M30: 0 | N30: 1 | O30: Jared Smith | P30: N/A | Q30: SAP Support Team | R30: 6 | S30: 1 | T30: N/A | U30: N/A | V30: New Ticket | W30: {=IF(H30="Request","No SLA for Request", IF(F30="Emergency",B30+(4/24), WORKDAY(B30, _xlfn.IFS(F30="High", 3, F30="Normal", 5, F30="Low", 10))))} -> 43791.858 | X30: =IF(K30>=W30,"Yes",IF(W30="No SLA for Request","N/A","No")) -> Yes
A31: 111331 | B31: 43761.71 | C31: Delete Or Rollback A Payroll Run | D31: Melody Thompson | E31: mthompson@yahoo.com | F31: Emergency | G31: SAP JDE Support Department | H31: Incident / Problem | I31: Web | J31: Closed | K31: 43773.659 | L31: 43763.708 | M31: 0 | N31: 1 | O31: Jared Smith | P31: N/A | Q31: JDE Support Team | R31: 30 | S31: 26 | T31: N/A | U31: N/A | V31: New Ticket | W31: {=IF(H31="Request","No SLA for Request", IF(F31="Emergency",B31+(4/24), WORKDAY(B31, _xlfn.IFS(F31="High", 3, F31="Normal", 5, F31="Low", 10))))} -> 43761.877 | X31: =IF(K31>=W31,"Yes",IF(W31="No SLA for Request","N/A","No")) -> Yes
A32: 111246 | B32: 43647.588 | C32: Batch Process Of Student Groups Not Working. | D32: Jasper John | E32: jasper.john@gmail.com | F32: Emergency | G32: SAP JDE Support Department | H32: Incident / Problem | I32: Web | J32: Closed | K32: 43760.758 | L32: 43648.088 | M32: 0 | N32: 1 | O32: Jared Smith | P32: N/A | Q32: SAP Support Team | R32: 14 | S32: 3 | T32: N/A | U32: N/A | V32: Close Ticket | W32: {=IF(H32="Request","No SLA for Request", IF(F32="Emergency",B32+(4/24), WORKDAY(B32, _xlfn.IFS(F32="High", 3, F32="Normal", 5, F32="Low", 10))))} -> 43647.754 | X32: =IF(K32>=W32,"Yes",IF(W32="No SLA for Request","N/A","No")) -> Yes
A33: 111265 | B33: 43664.585 | C33: Bpm Staging Error | D33: Atom Short | E33: atom.short@gmail.com | F33: Emergency | G33: InterN/Al Technical Department | H33: Incident / Problem | I33: Web | J33: Closed | K33: 43739.447 | L33: 43665.085 | M33: 0 | N33: 1 | O33: Stellar Murad | P33: N/A | Q33: Help Desk Team | R33: 7 | S33: 0 | T33: N/A | U33: N/A | V33: New Ticket | W33: {=IF(H33="Request","No SLA for Request", IF(F33="Emergency",B33+(4/24), WORKDAY(B33, _xlfn.IFS(F33="High", 3, F33="Normal", 5, F33="Low", 10))))} -> 43664.751 | X33: =IF(K33>=W33,"Yes",IF(W33="No SLA for Request","N/A","No")) -> Yes
A34: 111306 | B34: 43729.445 | C34: Palo Alto Device No Lights On Lan Ports | D34: Tomi Yamamoto | E34: tyamamoto@gmail.com | F34: Emergency | G34: InterN/Al Technical Department | H34: Incident / Problem | I34: Web | J34: Closed | K34: 43735.711 | L34: 43729.945 | M34: 0 | N34: 1 | O34: Stellar Murad | P34: N/A | Q34: Network Team | R34: 11 | S34: 2 | T34: N/A | U34: N/A | V34: New Ticket | W34: {=IF(H34="Request","No SLA for Request", IF(F34="Emergency",B34+(4/24), WORKDAY(B34, _xlfn.IFS(F34="High", 3, F34="Normal", 5, F34="Low", 10))))} -> 43729.612 | X34: =IF(K34>=W34,"Yes",IF(W34="No SLA for Request","N/A","No")) -> Yes
A35: 111147 | B35: 43543.409 | C35: Cannot Login In Sap | D35: Aurora Miller | E35: aurora.miller@outlook.com | F35: Emergency | G35: SAP JDE Support Department | H35: Incident / Problem | I35: Web | J35: Closed | K35: 43719.726 | L35: 43543.909 | M35: 0 | N35: 1 | O35: Jared Smith | P35: N/A | Q35: SAP Support Team | R35: 24 | S35: 9 | T35: N/A | U35: N/A | V35: Close Ticket | W35: {=IF(H35="Request","No SLA for Request", IF(F35="Emergency",B35+(4/24), WORKDAY(B35, _xlfn.IFS(F35="High", 3, F35="Normal", 5, F35="Low", 10))))} -> 43543.576 | X35: =IF(K35>=W35,"Yes",IF(W35="No SLA for Request","N/A","No")) -> Yes
A36: 111254 | B36: 43655.358 | C36: Sap Is Not Accessible | D36: Jasper John | E36: jasper.john@gmail.com | F36: Emergency | G36: SAP JDE Support Department | H36: Incident / Problem | I36: Web | J36: Closed | K36: 43719.724 | L36: N/A | M36: 0 | N36: 1 | O36: Jared Smith | P36: N/A | Q36: SAP Support Team | R36: 21 | S36: 6 | T36: N/A | U36: N/A | V36: Close Ticket | W36: {=IF(H36="Request","No SLA for Request", IF(F36="Emergency",B36+(4/24), WORKDAY(B36, _xlfn.IFS(F36="High", 3, F36="Normal", 5, F36="Low", 10))))} -> 43655.525 | X36: =IF(K36>=W36,"Yes",IF(W36="No SLA for Request","N/A","No")) -> Yes
A37: 111283 | B37: 43685.303 | C37: Jde Prod Not Available | D37: Julius Wright | E37: jwirght@outlook.com | F37: Emergency | G37: SAP JDE Support Department | H37: Incident / Problem | I37: Web | J37: Closed | K37: 43705.465 | L37: 43685.803 | M37: 0 | N37: 1 | O37: Jared Smith | P37: N/A | Q37: JDE Support Team | R37: 9 | S37: 1 | T37: N/A | U37: N/A | V37: New Ticket | W37: {=IF(H37="Request","No SLA for Request", IF(F37="Emergency",B37+(4/24), WORKDAY(B37, _xlfn.IFS(F37="High", 3, F37="Normal", 5, F37="Low", 10))))} -> 43685.47 | X37: =IF(K37>=W37,"Yes",IF(W37="No SLA for Request","N/A","No")) -> Yes
A38: 111258 | B38: 43657.338 | C38: Error 504 | D38: Marvin Peters | E38: mpeters@outlook.com | F38: Emergency | G38: SAP JDE Support Department | H38: Incident / Problem | I38: Web | J38: Closed | K38: 43663.742 | L38: 43657.838 | M38: 0 | N38: 1 | O38: Jared Smith | P38: N/A | Q38: SAP Support Team | R38: 10 | S38: 5 | T38: N/A | U38: N/A | V38: Close Ticket | W38: {=IF(H38="Request","No SLA for Request", IF(F38="Emergency",B38+(4/24), WORKDAY(B38, _xlfn.IFS(F38="High", 3, F38="Normal", 5, F38="Low", 10))))} -> 43657.505 | X38: =IF(K38>=W38,"Yes",IF(W38="No SLA for Request","N/A","No")) -> Yes
A39: 111222 | B39: 43620.398 | C39: Create Specific Function In The Responsibility | D39: Wilson Campus | E39: wilson.campus@yahoo.com | F39: Emergency | G39: SAP JDE Support Department | H39: Incident / Problem | I39: Web | J39: Closed | K39: 43630.589 | L39: 43623.708 | M39: 0 | N39: 1 | O39: Jared Smith | P39: N/A | Q39: JDE Support Team | R39: 25 | S39: 8 | T39: N/A | U39: N/A | V39: New Ticket | W39: {=IF(H39="Request","No SLA for Request", IF(F39="Emergency",B39+(4/24), WORKDAY(B39, _xlfn.IFS(F39="High", 3, F39="Normal", 5, F39="Low", 10))))} -> 43620.565 | X39: =IF(K39>=W39,"Yes",IF(W39="No SLA for Request","N/A","No")) -> Yes
A40: 111210 | B40: 43612.449 | C40: Error Loading Position List In Authority To Travel | D40: Paul Jiggins | E40: pjiggins@yahoo.com | F40: Emergency | G40: SAP JDE Support Department | H40: Incident / Problem | I40: Web | J40: Closed | K40: 43630.579 | L40: 43626.708 | M40: 0 | N40: 1 | O40: Jared Smith | P40: N/A | Q40: JDE Support Team | R40: 9 | S40: 5 | T40: N/A | U40: N/A | V40: New Ticket | W40: {=IF(H40="Request","No SLA for Request", IF(F40="Emergency",B40+(4/24), WORKDAY(B40, _xlfn.IFS(F40="High", 3, F40="Normal", 5, F40="Low", 10))))} -> 43612.616 | X40: =IF(K40>=W40,"Yes",IF(W40="No SLA for Request","N/A","No")) -> Yes
A41: 111168 | B41: 43559.667 | C41: Jde Prod Slowdown | D41: Julius Wright | E41: jwirght@outlook.com | F41: Emergency | G41: SAP JDE Support Department | H41: Incident / Problem | I41: Web | J41: Closed | K41: 43630.575 | L41: 43560.167 | M41: 0 | N41: 1 | O41: Jared Smith | P41: N/A | Q41: JDE Support Team | R41: 25 | S41: 5 | T41: N/A | U41: N/A | V41: Close Ticket | W41: {=IF(H41="Request","No SLA for Request", IF(F41="Emergency",B41+(4/24), WORKDAY(B41, _xlfn.IFS(F41="High", 3, F41="Normal", 5, F41="Low", 10))))} -> 43559.833 | X41: =IF(K41>=W41,"Yes",IF(W41="No SLA for Request","N/A","No")) -> Yes
A42: 111225 | B42: 43622.359 | C42: UN/Able To Login In Prod Instance | D42: John Brown | E42: jbrown@outlook.com | F42: Emergency | G42: SAP JDE Support Department | H42: Incident / Problem | I42: Web | J42: Closed | K42: 43629.546 | L42: 43622.859 | M42: 0 | N42: 1 | O42: Jared Smith | P42: N/A | Q42: SAP Support Team | R42: 11 | S42: 1 | T42: N/A | U42: N/A | V42: Close Ticket | W42: {=IF(H42="Request","No SLA for Request", IF(F42="Emergency",B42+(4/24), WORKDAY(B42, _xlfn.IFS(F42="High", 3, F42="Normal", 5, F42="Low", 10))))} -> 43622.526 | X42: =IF(K42>=W42,"Yes",IF(W42="No SLA for Request","N/A","No")) -> Yes
A43: 111219 | B43: 43616.483 | C43: Oracle Hrms - Element Entry Setup | D43: Wilson Campus | E43: wilson.campus@yahoo.com | F43: Emergency | G43: SAP JDE Support Department | H43: Request | I43: Web | J43: Closed | K43: 43626.619 | L43: 43626.708 | M43: 0 | N43: 1 | O43: Jared Smith | P43: N/A | Q43: JDE Support Team | R43: 14 | S43: 6 | T43: N/A | U43: N/A | V43: New Ticket | W43: {=IF(H43="Request","No SLA for Request", IF(F43="Emergency",B43+(4/24), WORKDAY(B43, _xlfn.IFS(F43="High", 3, F43="Normal", 5, F43="Low", 10))))} -> No SLA for Request | X43: =IF(K43>=W43,"Yes",IF(W43="No SLA for Request","N/A","No")) -> N/A
A44: 111188 | B44: 43584.637 | C44: Jde Prod - Error In Workflow Background Process | D44: Julius Wright | E44: jwirght@outlook.com | F44: Emergency | G44: SAP JDE Support Department | H44: Incident / Problem | I44: Web | J44: Closed | K44: 43620.722 | L44: 43585.137 | M44: 0 | N44: 1 | O44: Jared Smith | P44: N/A | Q44: JDE Support Team | R44: 45 | S44: 3 | T44: N/A | U44: N/A | V44: Close Ticket | W44: {=IF(H44="Request","No SLA for Request", IF(F44="Emergency",B44+(4/24), WORKDAY(B44, _xlfn.IFS(F44="High", 3, F44="Normal", 5, F44="Low", 10))))} -> 43584.804 | X44: =IF(K44>=W44,"Yes",IF(W44="No SLA for Request","N/A","No")) -> Yes
A45: 111184 | B45: 43579.596 | C45: Jde Prod - Slowdown Access | D45: Julius Wright | E45: jwirght@outlook.com | F45: Emergency | G45: SAP JDE Support Department | H45: Incident / Problem | I45: Web | J45: Closed | K45: 43599.806 | L45: 43580.096 | M45: 0 | N45: 1 | O45: Jared Smith | P45: N/A | Q45: JDE Support Team | R45: 14 | S45: 1 | T45: N/A | U45: N/A | V45: New Ticket | W45: {=IF(H45="Request","No SLA for Request", IF(F45="Emergency",B45+(4/24), WORKDAY(B45, _xlfn.IFS(F45="High", 3, F45="Normal", 5, F45="Low", 10))))} -> 43579.762 | X45: =IF(K45>=W45,"Yes",IF(W45="No SLA for Request","N/A","No")) -> Yes
A46: 111171 | B46: 43563.369 | C46: Jde Prod Error - Fail Web Server | D46: Julius Wright | E46: jwirght@outlook.com | F46: Emergency | G46: SAP JDE Support Department | H46: Incident / Problem | I46: Web | J46: Closed | K46: 43584.713 | L46: 43563.869 | M46: 0 | N46: 1 | O46: Jared Smith | P46: N/A | Q46: JDE Support Team | R46: 15 | S46: 1 | T46: N/A | U46: N/A | V46: New Ticket | W46: {=IF(H46="Request","No SLA for Request", IF(F46="Emergency",B46+(4/24), WORKDAY(B46, _xlfn.IFS(F46="High", 3, F46="Normal", 5, F46="Low", 10))))} -> 43563.535 | X46: =IF(K46>=W46,"Yes",IF(W46="No SLA for Request","N/A","No")) -> Yes
A47: 111181 | B47: 43577.38 | C47: Jde Prod - Request Not Completing | D47: Julius Wright | E47: jwirght@outlook.com | F47: Emergency | G47: SAP JDE Support Department | H47: Incident / Problem | I47: Web | J47: Closed | K47: 43579.735 | L47: 43577.88 | M47: 0 | N47: 1 | O47: Jared Smith | P47: N/A | Q47: JDE Support Team | R47: 18 | S47: 5 | T47: N/A | U47: N/A | V47: New Ticket | W47: {=IF(H47="Request","No SLA for Request", IF(F47="Emergency",B47+(4/24), WORKDAY(B47, _xlfn.IFS(F47="High", 3, F47="Normal", 5, F47="Low", 10))))} -> 43577.547 | X47: =IF(K47>=W47,"Yes",IF(W47="No SLA for Request","N/A","No")) -> Yes
A48: 111178 | B48: 43572.475 | C48: Jde Prod Slowdown | D48: Julius Wright | E48: jwirght@outlook.com | F48: Emergency | G48: SAP JDE Support Department | H48: Incident / Problem | I48: Web | J48: Closed | K48: 43579.734 | L48: 43572.975 | M48: 0 | N48: 1 | O48: Jared Smith | P48: N/A | Q48: JDE Support Team | R48: 13 | S48: 1 | T48: N/A | U48: N/A | V48: New Ticket | W48: {=IF(H48="Request","No SLA for Request", IF(F48="Emergency",B48+(4/24), WORKDAY(B48, _xlfn.IFS(F48="High", 3, F48="Normal", 5, F48="Low", 10))))} -> 43572.642 | X48: =IF(K48>=W48,"Yes",IF(W48="No SLA for Request","N/A","No")) -> Yes
... A75: 111382 | B75: 43868.647 | C75: Set Up And Configuration Of Eset | D75: Tomi Yamamoto | E75: tyamamoto@gmail.com | F75: High | G75: InterN/Al Technical Department | H75: Request | I75: Web | J75: Closed | K75: 44025.51 | L75: 43869.147 | M75: 0 | N75: 1 | O75: Jared Smith | P75: N/A | Q75: Network Team | R75: 4 | S75: 0 | T75: N/A | U75: N/A | V75: New Ticket | W75: {=IF(H75="Request","No SLA for Request", IF(F75="Emergency",B75+(4/24), WORKDAY(B75, _xlfn.IFS(F75="High", 3, F75="Normal", 5, F75="Low", 10))))} -> No SLA for Request | X75: =IF(K75>=W75,"Yes",IF(W75="No SLA for Request","N/A","No")) -> N/A
A76: 111456 | B76: 44014.508 | C76: Notifications | D76: Jane Wilberts | E76: jwilberts@mailiN/Ator.com | F76: High | G76: SAP JDE Support Department | H76: Request | I76: Web | J76: Closed | K76: 44018.733 | L76: N/A | M76: 0 | N76: 1 | O76: Jared Smith | P76: N/A | Q76: JDE Support Team | R76: 4 | S76: 1 | T76: NON-PROD | U76: TEST | V76: Close Ticket | W76: {=IF(H76="Request","No SLA for Request", IF(F76="Emergency",B76+(4/24), WORKDAY(B76, _xlfn.IFS(F76="High", 3, F76="Normal", 5, F76="Low", 10))))} -> No SLA for Request | X76: =IF(K76>=W76,"Yes",IF(W76="No SLA for Request","N/A","No")) -> N/A
A77: 111417 | B77: 43950.323 | C77: Workspace Problem After Bpm Version Upgrade | D77: Willard Smith | E77: willard.smith@mailiN/Ator.com | F77: High | G77: InterN/Al Technical Department | H77: Incident / Problem | I77: Web | J77: Closed | K77: 44007.694 | L77: 43950.823 | M77: 0 | N77: 1 | O77: Jared Smith | P77: N/A | Q77: BPM - ProcessMaker Support Team | R77: 6 | S77: 4 | T77: N/A | U77: PRODUCTION | V77: Open | W77: {=IF(H77="Request","No SLA for Request", IF(F77="Emergency",B77+(4/24), WORKDAY(B77, _xlfn.IFS(F77="High", 3, F77="Normal", 5, F77="Low", 10))))} -> 43955 | X77: =IF(K77>=W77,"Yes",IF(W77="No SLA for Request","N/A","No")) -> Yes
A78: 111434 | B78: 43985.688 | C78: Find Oracle Table Of Position Occupancy | D78: Melody Thompson | E78: mthompson@yahoo.com | F78: High | G78: SAP JDE Support Department | H78: Request | I78: Web | J78: Closed | K78: 44006.652 | L78: N/A | M78: 0 | N78: 1 | O78: Jared Smith | P78: N/A | Q78: JDE Support Team | R78: 16 | S78: 10 | T78: PROD | U78: PRODUCTION | V78: New Ticket | W78: {=IF(H78="Request","No SLA for Request", IF(F78="Emergency",B78+(4/24), WORKDAY(B78, _xlfn.IFS(F78="High", 3, F78="Normal", 5, F78="Low", 10))))} -> No SLA for Request | X78: =IF(K78>=W78,"Yes",IF(W78="No SLA for Request","N/A","No")) -> N/A
A79: 111437 | B79: 43990.483 | C79: Replace Actual Email In Test Instance | D79: Melody Thompson | E79: mthompson@yahoo.com | F79: High | G79: SAP JDE Support Department | H79: Request | I79: Web | J79: Closed | K79: 43997.363 | L79: N/A | M79: 0 | N79: 1 | O79: Jared Smith | P79: N/A | Q79: JDE Support Team | R79: 13 | S79: 2 | T79: NON-PROD | U79: TEST | V79: Close Ticket | W79: {=IF(H79="Request","No SLA for Request", IF(F79="Emergency",B79+(4/24), WORKDAY(B79, _xlfn.IFS(F79="High", 3, F79="Normal", 5, F79="Low", 10))))} -> No SLA for Request | X79: =IF(K79>=W79,"Yes",IF(W79="No SLA for Request","N/A","No")) -> N/A
A80: 111353 | B80: 43803.594 | C80: Can'T Access My Account | D80: Marvin Peters | E80: mpeters@outlook.com | F80: High | G80: SAP JDE Support Department | H80: Incident / Problem | I80: Web | J80: Closed | K80: 43962.721 | L80: N/A | M80: 0 | N80: 1 | O80: Jared Smith | P80: N/A | Q80: SAP Support Team | R80: 79 | S80: 4 | T80: PROD | U80: PRODUCTION | V80: New Ticket | W80: {=IF(H80="Request","No SLA for Request", IF(F80="Emergency",B80+(4/24), WORKDAY(B80, _xlfn.IFS(F80="High", 3, F80="Normal", 5, F80="Low", 10))))} -> 43808 | X80: =IF(K80>=W80,"Yes",IF(W80="No SLA for Request","N/A","No")) -> Yes
A81: 111320 | B81: 43746.651 | C81: Deferred Po Transactions | D81: Reah Junes | E81: rjunes@yahoo.com | F81: High | G81: SAP JDE Support Department | H81: Incident / Problem | I81: Web | J81: Closed | K81: 43958.558 | L81: N/A | M81: 0 | N81: 1 | O81: Jared Smith | P81: N/A | Q81: JDE Support Team | R81: 55 | S81: 9 | T81: PROD | U81: PRODUCTION | V81: New Ticket | W81: {=IF(H81="Request","No SLA for Request", IF(F81="Emergency",B81+(4/24), WORKDAY(B81, _xlfn.IFS(F81="High", 3, F81="Normal", 5, F81="Low", 10))))} -> 43749 | X81: =IF(K81>=W81,"Yes",IF(W81="No SLA for Request","N/A","No")) -> Yes
A82: 111390 | B82: 43879.462 | C82: Expense Report Stuck At Ame Approval Process/Block | D82: Kenex Willows | E82: kwillows@yahoo.com | F82: High | G82: SAP JDE Support Department | H82: Incident / Problem | I82: Web | J82: Closed | K82: 43957.657 | L82: N/A | M82: 0 | N82: 1 | O82: Jared Smith | P82: N/A | Q82: JDE Support Team | R82: 24 | S82: 2 | T82: PROD | U82: PRODUCTION | V82: Close Ticket | W82: {=IF(H82="Request","No SLA for Request", IF(F82="Emergency",B82+(4/24), WORKDAY(B82, _xlfn.IFS(F82="High", 3, F82="Normal", 5, F82="Low", 10))))} -> 43882 | X82: =IF(K82>=W82,"Yes",IF(W82="No SLA for Request","N/A","No")) -> Yes
A83: 111409 | B83: 43936.49 | C83: Server Failed To Start (Application Server) | D83: John Brown | E83: jbrown@outlook.com | F83: High | G83: SAP JDE Support Department | H83: Incident / Problem | I83: Web | J83: Closed | K83: 43937.649 | L83: N/A | M83: 0 | N83: 1 | O83: Jared Smith | P83: N/A | Q83: AWS Team | R83: 6 | S83: 1 | T83: NON-PROD | U83: DEVELOPMENT | V83: Close Ticket | W83: {=IF(H83="Request","No SLA for Request", IF(F83="Emergency",B83+(4/24), WORKDAY(B83, _xlfn.IFS(F83="High", 3, F83="Normal", 5, F83="Low", 10))))} -> 43941 | X83: =IF(K83>=W83,"Yes",IF(W83="No SLA for Request","N/A","No")) -> No
A84: 111383 | B84: 43871.419 | C84: Jde Approval Cannot Be Approved Or Transferred | D84: Kenex Willows | E84: kwillows@yahoo.com | F84: High | G84: SAP JDE Support Department | H84: Incident / Problem | I84: Web | J84: Closed | K84: 43929.715 | L84: N/A | M84: 0 | N84: 1 | O84: Jared Smith | P84: N/A | Q84: JDE Support Team | R84: 17 | S84: 2 | T84: PROD | U84: DEVELOPMENT | V84: New Ticket | W84: {=IF(H84="Request","No SLA for Request", IF(F84="Emergency",B84+(4/24), WORKDAY(B84, _xlfn.IFS(F84="High", 3, F84="Normal", 5, F84="Low", 10))))} -> 43874 | X84: =IF(K84>=W84,"Yes",IF(W84="No SLA for Request","N/A","No")) -> Yes
A85: 111404 | B85: 43913.672 | C85: Cs 9.2 Server Issue | D85: John Brown | E85: jbrown@outlook.com | F85: High | G85: SAP JDE Support Department | H85: Incident / Problem | I85: Web | J85: Closed | K85: 43923.724 | L85: N/A | M85: 0 | N85: 1 | O85: Jared Smith | P85: N/A | Q85: SAP Support Team | R85: 6 | S85: 1 | T85: NON-PROD | U85: DEVELOPMENT | V85: Close Ticket | W85: {=IF(H85="Request","No SLA for Request", IF(F85="Emergency",B85+(4/24), WORKDAY(B85, _xlfn.IFS(F85="High", 3, F85="Normal", 5, F85="Low", 10))))} -> 43916 | X85: =IF(K85>=W85,"Yes",IF(W85="No SLA for Request","N/A","No")) -> Yes
A86: 111401 | B86: 43903.467 | C86: Application Designer In 9.0 Prod | D86: John Brown | E86: jbrown@outlook.com | F86: High | G86: SAP JDE Support Department | H86: Incident / Problem | I86: Web | J86: Closed | K86: 43914.714 | L86: N/A | M86: 0 | N86: 1 | O86: Jared Smith | P86: N/A | Q86: SAP Support Team | R86: 19 | S86: 1 | T86: PROD | U86: DEVELOPMENT | V86: New Ticket | W86: {=IF(H86="Request","No SLA for Request", IF(F86="Emergency",B86+(4/24), WORKDAY(B86, _xlfn.IFS(F86="High", 3, F86="Normal", 5, F86="Low", 10))))} -> 43908 | X86: =IF(K86>=W86,"Yes",IF(W86="No SLA for Request","N/A","No")) -> Yes
A87: 111393 | B87: 43889.575 | C87: Can'T Access Test Instance | D87: Jane Wilberts | E87: jwilberts@mailiN/Ator.com | F87: High | G87: SAP JDE Support Department | H87: Incident / Problem | I87: Web | J87: Closed | K87: 43913.546 | L87: N/A | M87: 0 | N87: 1 | O87: Jared Smith | P87: N/A | Q87: JDE Support Team | R87: 29 | S87: 3 | T87: NON-PROD | U87: DEVELOPMENT | V87: New Ticket | W87: {=IF(H87="Request","No SLA for Request", IF(F87="Emergency",B87+(4/24), WORKDAY(B87, _xlfn.IFS(F87="High", 3, F87="Normal", 5, F87="Low", 10))))} -> 43894 | X87: =IF(K87>=W87,"Yes",IF(W87="No SLA for Request","N/A","No")) -> Yes
A88: 111391 | B88: 43887.65 | C88: Prod: Security Changed In Latest Start Date Field | D88: Melody Thompson | E88: mthompson@yahoo.com | F88: High | G88: SAP JDE Support Department | H88: Request | I88: Web | J88: Closed | K88: 43895.591 | L88: N/A | M88: 0 | N88: 1 | O88: Jared Smith | P88: N/A | Q88: JDE Support Team | R88: 20 | S88: 10 | T88: PROD | U88: DEVELOPMENT | V88: New Ticket | W88: {=IF(H88="Request","No SLA for Request", IF(F88="Emergency",B88+(4/24), WORKDAY(B88, _xlfn.IFS(F88="High", 3, F88="Normal", 5, F88="Low", 10))))} -> No SLA for Request | X88: =IF(K88>=W88,"Yes",IF(W88="No SLA for Request","N/A","No")) -> N/A
A89: 111380 | B89: 43860.442 | C89: Reset Of Palo Alto | D89: Tomi Yamamoto | E89: tyamamoto@gmail.com | F89: High | G89: InterN/Al Technical Department | H89: Request | I89: Web | J89: Closed | K89: 43868.692 | L89: 43860.942 | M89: 0 | N89: 1 | O89: Stellar Murad | P89: N/A | Q89: Network Team | R89: 5 | S89: 0 | T89: N/A | U89: N/A | V89: New Ticket | W89: {=IF(H89="Request","No SLA for Request", IF(F89="Emergency",B89+(4/24), WORKDAY(B89, _xlfn.IFS(F89="High", 3, F89="Normal", 5, F89="Low", 10))))} -> No SLA for Request | X89: =IF(K89>=W89,"Yes",IF(W89="No SLA for Request","N/A","No")) -> N/A
A90: 111378 | B90: 43857.589 | C90: Sf Error | D90: Aurora Miller | E90: aurora.miller@outlook.com | F90: High | G90: SAP JDE Support Department | H90: Incident / Problem | I90: Web | J90: Closed | K90: 43861.692 | L90: N/A | M90: 0 | N90: 1 | O90: Jared Smith | P90: N/A | Q90: SAP Support Team | R90: 6 | S90: 5 | T90: PROD | U90: DEVELOPMENT | V90: Close Ticket | W90: {=IF(H90="Request","No SLA for Request", IF(F90="Emergency",B90+(4/24), WORKDAY(B90, _xlfn.IFS(F90="High", 3, F90="Normal", 5, F90="Low", 10))))} -> 43860 | X90: =IF(K90>=W90,"Yes",IF(W90="No SLA for Request","N/A","No")) -> Yes
A91: 111369 | B91: 43840.36 | C91: Slow Loading Of Sap Jan 10 2020 | D91: Jasper John | E91: jasper.john@gmail.com | F91: High | G91: SAP JDE Support Department | H91: Incident / Problem | I91: Web | J91: Closed | K91: 43857.736 | L91: N/A | M91: 0 | N91: 1 | O91: Jared Smith | P91: N/A | Q91: SAP Support Team | R91: 8 | S91: 1 | T91: PROD | U91: DEVELOPMENT | V91: New Ticket | W91: {=IF(H91="Request","No SLA for Request", IF(F91="Emergency",B91+(4/24), WORKDAY(B91, _xlfn.IFS(F91="High", 3, F91="Normal", 5, F91="Low", 10))))} -> 43845 | X91: =IF(K91>=W91,"Yes",IF(W91="No SLA for Request","N/A","No")) -> Yes
A92: 111318 | B92: 43742.599 | C92: Ame Approval Udpdates Not Reflecting In The Db | D92: Reah Junes | E92: rjunes@yahoo.com | F92: High | G92: SAP JDE Support Department | H92: Incident / Problem | I92: Web | J92: Closed | K92: 43845.721 | L92: N/A | M92: 0 | N92: 1 | O92: Jared Smith | P92: N/A | Q92: JDE Support Team | R92: 24 | S92: 4 | T92: PROD | U92: DEVELOPMENT | V92: New Ticket | W92: {=IF(H92="Request","No SLA for Request", IF(F92="Emergency",B92+(4/24), WORKDAY(B92, _xlfn.IFS(F92="High", 3, F92="Normal", 5, F92="Low", 10))))} -> 43747 | X92: =IF(K92>=W92,"Yes",IF(W92="No SLA for Request","N/A","No")) -> Yes
A93: 111361 | B93: 43822.708 | C93: Peoplesoft Restricted Service | D93: John Brown | E93: jbrown@outlook.com | F93: High | G93: SAP JDE Support Department | H93: Incident / Problem | I93: Web | J93: Closed | K93: 43838.443 | L93: 43823.208 | M93: 0 | N93: 1 | O93: Jared Smith | P93: N/A | Q93: SAP Support Team | R93: 12 | S93: 2 | T93: N/A | U93: N/A | V93: Close Ticket | W93: {=IF(H93="Request","No SLA for Request", IF(F93="Emergency",B93+(4/24), WORKDAY(B93, _xlfn.IFS(F93="High", 3, F93="Normal", 5, F93="Low", 10))))} -> 43825 | X93: =IF(K93>=W93,"Yes",IF(W93="No SLA for Request","N/A","No")) -> Yes
A94: 111360 | B94: 43818.375 | C94: Faculty Cannot Post Grade | D94: Aurora Miller | E94: aurora.miller@outlook.com | F94: High | G94: SAP JDE Support Department | H94: Incident / Problem | I94: Web | J94: Closed | K94: 43836.728 | L94: 43818.875 | M94: 0 | N94: 1 | O94: Jared Smith | P94: N/A | Q94: SAP Support Team | R94: 8 | S94: 3 | T94: N/A | U94: N/A | V94: New Ticket | W94: {=IF(H94="Request","No SLA for Request", IF(F94="Emergency",B94+(4/24), WORKDAY(B94, _xlfn.IFS(F94="High", 3, F94="Normal", 5, F94="Low", 10))))} -> 43823 | X94: =IF(K94>=W94,"Yes",IF(W94="No SLA for Request","N/A","No")) -> Yes
A95: 111358 | B95: 43810.59 | C95: UN/Able To Access The Cs 9.2 | D95: John Brown | E95: jbrown@outlook.com | F95: High | G95: SAP JDE Support Department | H95: Incident / Problem | I95: Web | J95: Closed | K95: 43822.647 | L95: 43811.09 | M95: 0 | N95: 1 | O95: Jared Smith | P95: N/A | Q95: AWS Team | R95: 6 | S95: 1 | T95: N/A | U95: N/A | V95: Close Ticket | W95: {=IF(H95="Request","No SLA for Request", IF(F95="Emergency",B95+(4/24), WORKDAY(B95, _xlfn.IFS(F95="High", 3, F95="Normal", 5, F95="Low", 10))))} -> 43815 | X95: =IF(K95>=W95,"Yes",IF(W95="No SLA for Request","N/A","No")) -> Yes
A96: 111351 | B96: 43797.474 | C96: Can'T Login User Account | D96: Marvin Peters | E96: mpeters@outlook.com | F96: High | G96: SAP JDE Support Department | H96: Incident / Problem | I96: Web | J96: Closed | K96: 43803.746 | L96: 43797.974 | M96: 0 | N96: 1 | O96: Jared Smith | P96: N/A | Q96: SAP Support Team | R96: 8 | S96: 1 | T96: N/A | U96: N/A | V96: Close Ticket | W96: {=IF(H96="Request","No SLA for Request", IF(F96="Emergency",B96+(4/24), WORKDAY(B96, _xlfn.IFS(F96="High", 3, F96="Normal", 5, F96="Low", 10))))} -> 43802 | X96: =IF(K96>=W96,"Yes",IF(W96="No SLA for Request","N/A","No")) -> Yes
A97: 111333 | B97: 43763.606 | C97: Integration Gateway | D97: John Brown | E97: jbrown@outlook.com | F97: High | G97: SAP JDE Support Department | H97: Incident / Problem | I97: Web | J97: Closed | K97: 43803.744 | L97: 43764.106 | M97: 0 | N97: 1 | O97: Jared Smith | P97: N/A | Q97: SAP Support Team | R97: 15 | S97: 3 | T97: N/A | U97: N/A | V97: Close Ticket | W97: {=IF(H97="Request","No SLA for Request", IF(F97="Emergency",B97+(4/24), WORKDAY(B97, _xlfn.IFS(F97="High", 3, F97="Normal", 5, F97="Low", 10))))} -> 43768 | X97: =IF(K97>=W97,"Yes",IF(W97="No SLA for Request","N/A","No")) -> Yes
A98: 111346 | B98: 43789.503 | C98: Jde Prod Error Page Upon Login | D98: Julius Wright | E98: jwirght@outlook.com | F98: High | G98: SAP JDE Support Department | H98: Incident / Problem | I98: Web | J98: Closed | K98: 43797.703 | L98: 43790.003 | M98: 0 | N98: 1 | O98: Jared Smith | P98: N/A | Q98: JDE Support Team | R98: 25 | S98: 2 | T98: N/A | U98: N/A | V98: New Ticket | W98: {=IF(H98="Request","No SLA for Request", IF(F98="Emergency",B98+(4/24), WORKDAY(B98, _xlfn.IFS(F98="High", 3, F98="Normal", 5, F98="Low", 10))))} -> 43794 | X98: =IF(K98>=W98,"Yes",IF(W98="No SLA for Request","N/A","No")) -> Yes
A99: 111227 | B99: 43623.596 | C99: Adding Of Subject Enrollment Issue | D99: Aurora Miller | E99: aurora.miller@outlook.com | F99: High | G99: SAP JDE Support Department | H99: Incident / Problem | I99: Web | J99: Closed | K99: 43790.746 | L99: 43624.096 | M99: 0 | N99: 1 | O99: Jared Smith | P99: N/A | Q99: SAP Support Team | R99: 32 | S99: 4 | T99: N/A | U99: N/A | V99: Close Ticket | W99: {=IF(H99="Request","No SLA for Request", IF(F99="Emergency",B99+(4/24), WORKDAY(B99, _xlfn.IFS(F99="High", 3, F99="Normal", 5, F99="Low", 10))))} -> 43628 | X99: =IF(K99>=W99,"Yes",IF(W99="No SLA for Request","N/A","No")) -> Yes
A100: 111334 | B100: 43763.622 | C100: Palo Alto Update | D100: Jane Wilberts | E100: jwilberts@mailiN/Ator.com | F100: High | G100: InterN/Al Technical Department | H100: Incident / Problem | I100: Web | J100: Closed | K100: 43775.72 | L100: 43764.122 | M100: 0 | N100: 1 | O100: Stellar Murad | P100: N/A | Q100: Network Team | R100: 6 | S100: 0 | T100: N/A | U100: N/A | V100: Close Ticket | W100: {=IF(H100="Request","No SLA for Request", IF(F100="Emergency",B100+(4/24), WORKDAY(B100, _xlfn.IFS(F100="High", 3, F100="Normal", 5, F100="Low", 10))))} -> 43768 | X100: =IF(K100>=W100,"Yes",IF(W100="No SLA for Request","N/A","No")) -> Yes
A101: 111322 | B101: 43749.571 | C101: UN/Able To Print Approved Certificate Of Service | D101: Troy Daniels | E101: troy.daniels@outlook.com | F101: High | G101: SAP JDE Support Department | H101: Incident / Problem | I101: Web | J101: Closed | K101: 43759.749 | L101: 43754.708 | M101: 0 | N101: 1 | O101: Jared Smith | P101: N/A | Q101: JDE Support Team | R101: 14 | S101: 7 | T101: N/A | U101: N/A | V101: New Ticket | W101: {=IF(H101="Request","No SLA for Request", IF(F101="Emergency",B101+(4/24), WORKDAY(B101, _xlfn.IFS(F101="High", 3, F101="Normal", 5, F101="Low", 10))))} -> 43754 | X101: =IF(K101>=W101,"Yes",IF(W101="No SLA for Request","N/A","No")) -> Yes
A102: 111312 | B102: 43739.44 | C102: Palo Alto Blocking Internet Of User | D102: Tomi Yamamoto | E102: tyamamoto@gmail.com | F102: High | G102: InterN/Al Technical Department | H102: Incident / Problem | I102: Web | J102: Closed | K102: 43759.574 | L102: 43739.94 | M102: 0 | N102: 1 | O102: Stellar Murad | P102: N/A | Q102: Network Team | R102: 4 | S102: 0 | T102: N/A | U102: N/A | V102: New Ticket | W102: {=IF(H102="Request","No SLA for Request", IF(F102="Emergency",B102+(4/24), WORKDAY(B102, _xlfn.IFS(F102="High", 3, F102="Normal", 5, F102="Low", 10))))} -> 43742 | X102: =IF(K102>=W102,"Yes",IF(W102="No SLA for Request","N/A","No")) -> Yes
A103: 111301 | B103: 43725.419 | C103: Password Reset | D103: Tomi Yamamoto | E103: tyamamoto@gmail.com | F103: High | G103: InterN/Al Technical Department | H103: Request | I103: Web | J103: Closed | K103: 43759.573 | L103: 43725.919 | M103: 0 | N103: 1 | O103: Stellar Murad | P103: N/A | Q103: Network Team | R103: 10 | S103: 2 | T103: N/A | U103: N/A | V103: New Ticket | W103: {=IF(H103="Request","No SLA for Request", IF(F103="Emergency",B103+(4/24), WORKDAY(B103, _xlfn.IFS(F103="High", 3, F103="Normal", 5, F103="Low", 10))))} -> No SLA for Request | X103: =IF(K103>=W103,"Yes",IF(W103="No SLA for Request","N/A","No")) -> N/A
A104: 111325 | B104: 43752.699 | C104: Requesting For On-Site Visit | D104: Tomi Yamamoto | E104: tyamamoto@gmail.com | F104: High | G104: InterN/Al Technical Department | H104: Request | I104: Web | J104: Closed | K104: 43759.572 | L104: 43753.199 | M104: 0 | N104: 1 | O104: Stellar Murad | P104: N/A | Q104: Network Team | R104: 4 | S104: 0 | T104: N/A | U104: N/A | V104: New Ticket | W104: {=IF(H104="Request","No SLA for Request", IF(F104="Emergency",B104+(4/24), WORKDAY(B104, _xlfn.IFS(F104="High", 3, F104="Normal", 5, F104="Low", 10))))} -> No SLA for Request | X104: =IF(K104>=W104,"Yes",IF(W104="No SLA for Request","N/A","No")) -> N/A
... A111: 111297 | B111: 43717.447 | C111: Issue With JourN/Al Import Via JourN/Al Wizard | D111: Kimberly Jones | E111: kjones@outlook.com | F111: High | G111: SAP JDE Support Department | H111: Incident / Problem | I111: Web | J111: Closed | K111: 43734.703 | L111: 43731.729 | M111: 0 | N111: 1 | O111: Jared Smith | P111: N/A | Q111: JDE Support Team | R111: 32 | S111: 8 | T111: N/A | U111: N/A | V111: New Ticket | W111: {=IF(H111="Request","No SLA for Request", IF(F111="Emergency",B111+(4/24), WORKDAY(B111, _xlfn.IFS(F111="High", 3, F111="Normal", 5, F111="Low", 10))))} -> 43720 | X111: =IF(K111>=W111,"Yes",IF(W111="No SLA for Request","N/A","No")) -> Yes
A112: 111291 | B112: 43705.387 | C112: Jde Prod Slowdown | D112: Julius Wright | E112: jwirght@outlook.com | F112: High | G112: SAP JDE Support Department | H112: Incident / Problem | I112: Web | J112: Closed | K112: 43727.726 | L112: N/A | M112: 0 | N112: 1 | O112: Jared Smith | P112: N/A | Q112: JDE Support Team | R112: 12 | S112: 3 | T112: N/A | U112: N/A | V112: New Ticket | W112: {=IF(H112="Request","No SLA for Request", IF(F112="Emergency",B112+(4/24), WORKDAY(B112, _xlfn.IFS(F112="High", 3, F112="Normal", 5, F112="Low", 10))))} -> 43710 | X112: =IF(K112>=W112,"Yes",IF(W112="No SLA for Request","N/A","No")) -> Yes
A113: 111296 | B113: 43711.435 | C113: Jde Prod Error In Validation Of Dv | D113: Julius Wright | E113: jwirght@outlook.com | F113: High | G113: SAP JDE Support Department | H113: Incident / Problem | I113: Web | J113: Closed | K113: 43726.723 | L113: 43721.708 | M113: 0 | N113: 1 | O113: Jared Smith | P113: N/A | Q113: JDE Support Team | R113: 19 | S113: 1 | T113: N/A | U113: N/A | V113: New Ticket | W113: {=IF(H113="Request","No SLA for Request", IF(F113="Emergency",B113+(4/24), WORKDAY(B113, _xlfn.IFS(F113="High", 3, F113="Normal", 5, F113="Low", 10))))} -> 43714 | X113: =IF(K113>=W113,"Yes",IF(W113="No SLA for Request","N/A","No")) -> Yes
A114: 111299 | B114: 43718.395 | C114: Jde Test: Error In Java Applet | D114: Melody Thompson | E114: mthompson@yahoo.com | F114: High | G114: SAP JDE Support Department | H114: Incident / Problem | I114: Web | J114: Closed | K114: 43725.71 | L114: 43718.895 | M114: 0 | N114: 1 | O114: Jared Smith | P114: N/A | Q114: JDE Support Team | R114: 7 | S114: 1 | T114: N/A | U114: N/A | V114: Open | W114: {=IF(H114="Request","No SLA for Request", IF(F114="Emergency",B114+(4/24), WORKDAY(B114, _xlfn.IFS(F114="High", 3, F114="Normal", 5, F114="Low", 10))))} -> 43721 | X114: =IF(K114>=W114,"Yes",IF(W114="No SLA for Request","N/A","No")) -> Yes
A115: 111120 | B115: 43502.405 | C115: [Sap] Term Activate A Student | D115: Michelle Walters | E115: michelle.walters@yahoo.com | F115: High | G115: SAP JDE Support Department | H115: Incident / Problem | I115: Web | J115: Closed | K115: 43719.727 | L115: N/A | M115: 0 | N115: 1 | O115: Jared Smith | P115: N/A | Q115: SAP Support Team | R115: 11 | S115: 4 | T115: N/A | U115: N/A | V115: New Ticket | W115: {=IF(H115="Request","No SLA for Request", IF(F115="Emergency",B115+(4/24), WORKDAY(B115, _xlfn.IFS(F115="High", 3, F115="Normal", 5, F115="Low", 10))))} -> 43507 | X115: =IF(K115>=W115,"Yes",IF(W115="No SLA for Request","N/A","No")) -> Yes
A116: 111114 | B116: 43497.425 | C116: Class Permission Of For 200-3 In Uplb | D116: Jasper John | E116: jasper.john@gmail.com | F116: High | G116: SAP JDE Support Department | H116: Request | I116: Web | J116: Closed | K116: 43719.727 | L116: N/A | M116: 0 | N116: 1 | O116: Jared Smith | P116: N/A | Q116: SAP Support Team | R116: 41 | S116: 5 | T116: N/A | U116: N/A | V116: New Ticket | W116: {=IF(H116="Request","No SLA for Request", IF(F116="Emergency",B116+(4/24), WORKDAY(B116, _xlfn.IFS(F116="High", 3, F116="Normal", 5, F116="Low", 10))))} -> No SLA for Request | X116: =IF(K116>=W116,"Yes",IF(W116="No SLA for Request","N/A","No")) -> N/A
A117: 111292 | B117: 43705.49 | C117: Update The Landing Page | D117: John Brown | E117: jbrown@outlook.com | F117: High | G117: SAP JDE Support Department | H117: Request | I117: Web | J117: Closed | K117: 43719.722 | L117: 43705.99 | M117: 0 | N117: 1 | O117: Jared Smith | P117: N/A | Q117: SAP Support Team | R117: 21 | S117: 5 | T117: N/A | U117: N/A | V117: New Ticket | W117: {=IF(H117="Request","No SLA for Request", IF(F117="Emergency",B117+(4/24), WORKDAY(B117, _xlfn.IFS(F117="High", 3, F117="Normal", 5, F117="Low", 10))))} -> No SLA for Request | X117: =IF(K117>=W117,"Yes",IF(W117="No SLA for Request","N/A","No")) -> N/A
A118: 111286 | B118: 43690.588 | C118: [Test Instance] Hung Concurrent Requests | D118: Kimberly Jones | E118: kjones@outlook.com | F118: High | G118: SAP JDE Support Department | H118: Incident / Problem | I118: Web | J118: Closed | K118: 43710.722 | L118: 43691.088 | M118: 0 | N118: 1 | O118: Jared Smith | P118: N/A | Q118: JDE Support Team | R118: 12 | S118: 2 | T118: N/A | U118: N/A | V118: New Ticket | W118: {=IF(H118="Request","No SLA for Request", IF(F118="Emergency",B118+(4/24), WORKDAY(B118, _xlfn.IFS(F118="High", 3, F118="Normal", 5, F118="Low", 10))))} -> 43693 | X118: =IF(K118>=W118,"Yes",IF(W118="No SLA for Request","N/A","No")) -> Yes
A119: 111288 | B119: 43697.383 | C119: Test Instance - License Expired | D119: Wilson Campus | E119: wilson.campus@yahoo.com | F119: High | G119: SAP JDE Support Department | H119: Incident / Problem | I119: Web | J119: Closed | K119: 43706.711 | L119: 43697.883 | M119: 0 | N119: 1 | O119: Jared Smith | P119: N/A | Q119: JDE Support Team | R119: 9 | S119: 3 | T119: N/A | U119: N/A | V119: New Ticket | W119: {=IF(H119="Request","No SLA for Request", IF(F119="Emergency",B119+(4/24), WORKDAY(B119, _xlfn.IFS(F119="High", 3, F119="Normal", 5, F119="Low", 10))))} -> 43700 | X119: =IF(K119>=W119,"Yes",IF(W119="No SLA for Request","N/A","No")) -> Yes
A120: 111206 | B120: 43606.634 | C120: Jde Prod Slowdown | D120: Julius Wright | E120: jwirght@outlook.com | F120: High | G120: SAP JDE Support Department | H120: Incident / Problem | I120: Web | J120: Closed | K120: 43704.358 | L120: 43607.134 | M120: 0 | N120: 1 | O120: Jared Smith | P120: N/A | Q120: JDE Support Team | R120: 46 | S120: 3 | T120: N/A | U120: N/A | V120: New Ticket | W120: {=IF(H120="Request","No SLA for Request", IF(F120="Emergency",B120+(4/24), WORKDAY(B120, _xlfn.IFS(F120="High", 3, F120="Normal", 5, F120="Low", 10))))} -> 43609 | X120: =IF(K120>=W120,"Yes",IF(W120="No SLA for Request","N/A","No")) -> Yes
A121: 111201 | B121: 43599.667 | C121: Expense Report Approval Hierarchy Issue | D121: Reah Junes | E121: rjunes@yahoo.com | F121: High | G121: SAP JDE Support Department | H121: Incident / Problem | I121: Web | J121: Closed | K121: 43699.787 | L121: 43696.708 | M121: 0 | N121: 1 | O121: Jared Smith | P121: N/A | Q121: JDE Support Team | R121: 20 | S121: 3 | T121: N/A | U121: N/A | V121: New Ticket | W121: {=IF(H121="Request","No SLA for Request", IF(F121="Emergency",B121+(4/24), WORKDAY(B121, _xlfn.IFS(F121="High", 3, F121="Normal", 5, F121="Low", 10))))} -> 43602 | X121: =IF(K121>=W121,"Yes",IF(W121="No SLA for Request","N/A","No")) -> Yes
A122: 111284 | B122: 43686.351 | C122: Can'T Access Odsm | D122: Marvin Peters | E122: mpeters@outlook.com | F122: High | G122: SAP JDE Support Department | H122: Incident / Problem | I122: Web | J122: Closed | K122: 43697.711 | L122: 43690.708 | M122: 0 | N122: 1 | O122: Jared Smith | P122: N/A | Q122: SAP Support Team | R122: 11 | S122: 2 | T122: N/A | U122: N/A | V122: New Ticket | W122: {=IF(H122="Request","No SLA for Request", IF(F122="Emergency",B122+(4/24), WORKDAY(B122, _xlfn.IFS(F122="High", 3, F122="Normal", 5, F122="Low", 10))))} -> 43691 | X122: =IF(K122>=W122,"Yes",IF(W122="No SLA for Request","N/A","No")) -> Yes
A123: 111281 | B123: 43679.615 | C123: Sap Production Slowdown | D123: Aurora Miller | E123: aurora.miller@outlook.com | F123: High | G123: SAP JDE Support Department | H123: Incident / Problem | I123: Web | J123: Closed | K123: 43683.356 | L123: N/A | M123: 0 | N123: 1 | O123: Jared Smith | P123: N/A | Q123: SAP Support Team | R123: 7 | S123: 2 | T123: N/A | U123: N/A | V123: New Ticket | W123: {=IF(H123="Request","No SLA for Request", IF(F123="Emergency",B123+(4/24), WORKDAY(B123, _xlfn.IFS(F123="High", 3, F123="Normal", 5, F123="Low", 10))))} -> 43684 | X123: =IF(K123>=W123,"Yes",IF(W123="No SLA for Request","N/A","No")) -> No
A124: 111273 | B124: 43674.672 | C124: Sql Error Message | D124: Aurora Miller | E124: aurora.miller@outlook.com | F124: High | G124: SAP JDE Support Department | H124: Incident / Problem | I124: Web | J124: Closed | K124: 43683.356 | L124: 43675.708 | M124: 0 | N124: 1 | O124: Jared Smith | P124: N/A | Q124: SAP Support Team | R124: 10 | S124: 6 | T124: N/A | U124: N/A | V124: New Ticket | W124: {=IF(H124="Request","No SLA for Request", IF(F124="Emergency",B124+(4/24), WORKDAY(B124, _xlfn.IFS(F124="High", 3, F124="Normal", 5, F124="Low", 10))))} -> 43677 | X124: =IF(K124>=W124,"Yes",IF(W124="No SLA for Request","N/A","No")) -> Yes
A125: 111269 | B125: 43669.463 | C125: Openvpn Problem | D125: Wilson Campus | E125: wilson.campus@yahoo.com | F125: High | G125: SAP JDE Support Department | H125: Incident / Problem | I125: Web | J125: Closed | K125: 43675.735 | L125: 43669.963 | M125: 0 | N125: 1 | O125: Jared Smith | P125: N/A | Q125: JDE Support Team | R125: 9 | S125: 2 | T125: N/A | U125: N/A | V125: New Ticket | W125: {=IF(H125="Request","No SLA for Request", IF(F125="Emergency",B125+(4/24), WORKDAY(B125, _xlfn.IFS(F125="High", 3, F125="Normal", 5, F125="Low", 10))))} -> 43672 | X125: =IF(K125>=W125,"Yes",IF(W125="No SLA for Request","N/A","No")) -> Yes
A126: 111252 | B126: 43654.664 | C126: MultiteN/Ant Error | D126: Atom Short | E126: atom.short@gmail.com | F126: High | G126: InterN/Al Technical Department | H126: Incident / Problem | I126: Web | J126: Closed | K126: 43664.73 | L126: 43655.164 | M126: 0 | N126: 1 | O126: Stellar Murad | P126: N/A | Q126: Help Desk Team | R126: 14 | S126: 2 | T126: N/A | U126: N/A | V126: New Ticket | W126: {=IF(H126="Request","No SLA for Request", IF(F126="Emergency",B126+(4/24), WORKDAY(B126, _xlfn.IFS(F126="High", 3, F126="Normal", 5, F126="Low", 10))))} -> 43657 | X126: =IF(K126>=W126,"Yes",IF(W126="No SLA for Request","N/A","No")) -> Yes
A127: 111248 | B127: 43650.654 | C127: Setup Of Earnings | D127: Wilson Campus | E127: wilson.campus@yahoo.com | F127: High | G127: SAP JDE Support Department | H127: Incident / Problem | I127: Web | J127: Closed | K127: 43661.728 | L127: 43656.708 | M127: 0 | N127: 1 | O127: Jared Smith | P127: N/A | Q127: JDE Support Team | R127: 9 | S127: 2 | T127: N/A | U127: N/A | V127: New Ticket | W127: {=IF(H127="Request","No SLA for Request", IF(F127="Emergency",B127+(4/24), WORKDAY(B127, _xlfn.IFS(F127="High", 3, F127="Normal", 5, F127="Low", 10))))} -> 43655 | X127: =IF(K127>=W127,"Yes",IF(W127="No SLA for Request","N/A","No")) -> Yes
A128: 111247 | B128: 43649.451 | C128: UN/Able To Tuition Calc For The Specific Student. | D128: Jasper John | E128: jasper.john@gmail.com | F128: High | G128: SAP JDE Support Department | H128: Incident / Problem | I128: Web | J128: Closed | K128: 43658.731 | L128: 43649.951 | M128: 0 | N128: 1 | O128: Jared Smith | P128: N/A | Q128: SAP Support Team | R128: 8 | S128: 2 | T128: N/A | U128: N/A | V128: Close Ticket | W128: {=IF(H128="Request","No SLA for Request", IF(F128="Emergency",B128+(4/24), WORKDAY(B128, _xlfn.IFS(F128="High", 3, F128="Normal", 5, F128="Low", 10))))} -> 43654 | X128: =IF(K128>=W128,"Yes",IF(W128="No SLA for Request","N/A","No")) -> Yes
A129: 111203 | B129: 43600.596 | C129: Jde Prod - Error Status Of Transactions | D129: Julius Wright | E129: jwirght@outlook.com | F129: High | G129: SAP JDE Support Department | H129: Incident / Problem | I129: Web | J129: Closed | K129: 43656.725 | L129: 43601.096 | M129: 0 | N129: 1 | O129: Jared Smith | P129: N/A | Q129: JDE Support Team | R129: 9 | S129: 2 | T129: N/A | U129: N/A | V129: New Ticket | W129: {=IF(H129="Request","No SLA for Request", IF(F129="Emergency",B129+(4/24), WORKDAY(B129, _xlfn.IFS(F129="High", 3, F129="Normal", 5, F129="Low", 10))))} -> 43605 | X129: =IF(K129>=W129,"Yes",IF(W129="No SLA for Request","N/A","No")) -> Yes
A130: 111180 | B130: 43572.725 | C130: [Oaf] $Custom_Top Path | D130: Winson Williams | E130: winson.williams@outlook.com | F130: High | G130: SAP JDE Support Department | H130: Request | I130: Web | J130: Closed | K130: 43655.731 | L130: 43573.225 | M130: 0 | N130: 1 | O130: Jared Smith | P130: N/A | Q130: JDE Support Team | R130: 15 | S130: 1 | T130: N/A | U130: N/A | V130: New Ticket | W130: {=IF(H130="Request","No SLA for Request", IF(F130="Emergency",B130+(4/24), WORKDAY(B130, _xlfn.IFS(F130="High", 3, F130="Normal", 5, F130="Low", 10))))} -> No SLA for Request | X130: =IF(K130>=W130,"Yes",IF(W130="No SLA for Request","N/A","No")) -> N/A
A131: 111242 | B131: 43643.692 | C131: Legal Case System Error | D131: Sheila Ryder | E131: sryder@mailiN/Ator.com | F131: High | G131: InterN/Al Technical Department | H131: Incident / Problem | I131: Web | J131: Open | K131: 43651.424 | L131: 43644.192 | M131: 1 | N131: 0 | O131: Jose Satary | P131: N/A | Q131: Help Desk Team | R131: 3 | S131: 1 | T131: N/A | U131: N/A | V131: New Ticket | W131: {=IF(H131="Request","No SLA for Request", IF(F131="Emergency",B131+(4/24), WORKDAY(B131, _xlfn.IFS(F131="High", 3, F131="Normal", 5, F131="Low", 10))))} -> 43648 | X131: =IF(K131>=W131,"Yes",IF(W131="No SLA for Request","N/A","No")) -> Yes
A132: 111243 | B132: 43643.709 | C132: Legal Case System - CrimiN/Al Case | D132: Sheila Ryder | E132: sryder@mailiN/Ator.com | F132: High | G132: InterN/Al Technical Department | H132: Incident / Problem | I132: Web | J132: Open | K132: 43651.424 | L132: 43644.209 | M132: 1 | N132: 0 | O132: Jared Smith | P132: N/A | Q132: Help Desk Team | R132: 3 | S132: 0 | T132: N/A | U132: N/A | V132: New Ticket | W132: {=IF(H132="Request","No SLA for Request", IF(F132="Emergency",B132+(4/24), WORKDAY(B132, _xlfn.IFS(F132="High", 3, F132="Normal", 5, F132="Low", 10))))} -> 43648 | X132: =IF(K132>=W132,"Yes",IF(W132="No SLA for Request","N/A","No")) -> Yes
A133: 111240 | B133: 43640.558 | C133: Vpn Access | D133: Marvin Peters | E133: mpeters@outlook.com | F133: High | G133: SAP JDE Support Department | H133: Incident / Problem | I133: Web | J133: Closed | K133: 43647.731 | L133: 43641.058 | M133: 0 | N133: 1 | O133: Jared Smith | P133: N/A | Q133: AWS Team | R133: 6 | S133: 1 | T133: N/A | U133: N/A | V133: Close Ticket | W133: {=IF(H133="Request","No SLA for Request", IF(F133="Emergency",B133+(4/24), WORKDAY(B133, _xlfn.IFS(F133="High", 3, F133="Normal", 5, F133="Low", 10))))} -> 43643 | X133: =IF(K133>=W133,"Yes",IF(W133="No SLA for Request","N/A","No")) -> Yes
A134: 111146 | B134: 43543.348 | C134: Jde Prod Slowdown | D134: Julius Wright | E134: jwirght@outlook.com | F134: High | G134: SAP JDE Support Department | H134: Incident / Problem | I134: Web | J134: Closed | K134: 43647.724 | L134: 43543.848 | M134: 0 | N134: 1 | O134: Jared Smith | P134: N/A | Q134: JDE Support Team | R134: 35 | S134: 5 | T134: N/A | U134: N/A | V134: New Ticket | W134: {=IF(H134="Request","No SLA for Request", IF(F134="Emergency",B134+(4/24), WORKDAY(B134, _xlfn.IFS(F134="High", 3, F134="Normal", 5, F134="Low", 10))))} -> 43546 | X134: =IF(K134>=W134,"Yes",IF(W134="No SLA for Request","N/A","No")) -> Yes
A135: 111220 | B135: 43616.555 | C135: Workflow Notification Won'T Start | D135: Vic Vincent | E135: vic.vincent@yahoo.com | F135: High | G135: SAP JDE Support Department | H135: Incident / Problem | I135: Web | J135: Closed | K135: 43637.756 | L135: 43626.708 | M135: 0 | N135: 1 | O135: Stellar Murad | P135: N/A | Q135: SAP Support Team | R135: 17 | S135: 1 | T135: N/A | U135: N/A | V135: New Ticket | W135: {=IF(H135="Request","No SLA for Request", IF(F135="Emergency",B135+(4/24), WORKDAY(B135, _xlfn.IFS(F135="High", 3, F135="Normal", 5, F135="Low", 10))))} -> 43621 | X135: =IF(K135>=W135,"Yes",IF(W135="No SLA for Request","N/A","No")) -> Yes
... A155: 111143 | B155: 43536.647 | C155: Jde Prod Slowdown | D155: Julius Wright | E155: jwirght@outlook.com | F155: High | G155: SAP JDE Support Department | H155: Incident / Problem | I155: Web | J155: Closed | K155: 43552.736 | L155: 43537.147 | M155: 0 | N155: 1 | O155: Jared Smith | P155: N/A | Q155: JDE Support Team | R155: 7 | S155: 2 | T155: N/A | U155: N/A | V155: New Ticket | W155: {=IF(H155="Request","No SLA for Request", IF(F155="Emergency",B155+(4/24), WORKDAY(B155, _xlfn.IFS(F155="High", 3, F155="Normal", 5, F155="Low", 10))))} -> 43539 | X155: =IF(K155>=W155,"Yes",IF(W155="No SLA for Request","N/A","No")) -> Yes
A156: 111122 | B156: 43502.683 | C156: Error In Submitting Updated Approved Pos | D156: Reah Junes | E156: rjunes@yahoo.com | F156: High | G156: SAP JDE Support Department | H156: Incident / Problem | I156: Web | J156: Closed | K156: 43546.777 | L156: N/A | M156: 0 | N156: 1 | O156: Jared Smith | P156: N/A | Q156: JDE Support Team | R156: 116 | S156: 37 | T156: N/A | U156: N/A | V156: New Ticket | W156: {=IF(H156="Request","No SLA for Request", IF(F156="Emergency",B156+(4/24), WORKDAY(B156, _xlfn.IFS(F156="High", 3, F156="Normal", 5, F156="Low", 10))))} -> 43507 | X156: =IF(K156>=W156,"Yes",IF(W156="No SLA for Request","N/A","No")) -> Yes
A157: 111138 | B157: 43523.44 | C157: UN/Able To Add Attachment In The Invoice | D157: Julius Wright | E157: jwirght@outlook.com | F157: High | G157: SAP JDE Support Department | H157: Incident / Problem | I157: Web | J157: Closed | K157: 43544.719 | L157: 43523.94 | M157: 0 | N157: 1 | O157: Jared Smith | P157: N/A | Q157: JDE Support Team | R157: 9 | S157: 1 | T157: N/A | U157: N/A | V157: New Ticket | W157: {=IF(H157="Request","No SLA for Request", IF(F157="Emergency",B157+(4/24), WORKDAY(B157, _xlfn.IFS(F157="High", 3, F157="Normal", 5, F157="Low", 10))))} -> 43528 | X157: =IF(K157>=W157,"Yes",IF(W157="No SLA for Request","N/A","No")) -> Yes
...

Sheet Pivot Table
A2: Total Tickets per Team
A3: Row Labels | B3: Count of Team Assigned | C3: Count of Team Assigned2
A4: AWS Team | B4: 5 | C4: 0.01607717
A5: BPM - ProcessMaker Support Team | B5: 2 | C5: 0.0064308682 | G5: 42
A6: Help Desk Team | B6: 6 | C6: 0.019292605
A7: JDE Support Team | B7: 170 | C7: 0.54662379
A8: Network Team | B8: 14 | C8: 0.045016077
A9: SAP Support Team | B9: 110 | C9: 0.35369775
A10: Workday Team | B10: 4 | C10: 0.012861736
A11: Grand Total | B11: 311 | C11: 1
S33: Total Tickets per Priority
S34: Row Labels | T34: Count of Priority
S35: Emergency | T35: 50
S36: High | T36: 112
S37: Low | T37: 39
S38: Normal | T38: 335
S39: Grand Total | T39: 536

Sheet Pivot chart
B3: Current Ticket per Status
B5: Row Labels | C5: Count of Ticket per Current Status
B6: Closed | C6: 288
B7: Open | C7: 15
B8: Resolved | C8: 8
B9: Grand Total | C9: 311

Sheet Ticket Viewer
B2: Enter Ticket Number:
B4: Subject | C4: =_xlfn.XLOOKUP(C2, helpdesk_tickets!A2:A537, helpdesk_tickets!C2:C537,"Not Found") -> Not Found
B5: From | C5: =_xlfn.XLOOKUP(C2,helpdesk_tickets!A2:A537, helpdesk_tickets!D2:D537,"Not Found") -> Not Found
B6: Date Created | C6: =_xlfn.XLOOKUP(C2,helpdesk_tickets!A2:A537,helpdesk_tickets!B2:B537,"Not Found") -> Not Found
B7: Priority | C7: =_xlfn.XLOOKUP(C2,helpdesk_tickets!A2:A537,helpdesk_tickets!F2:F537,"Not Found") -> Not Found
B8: Type | C8: =_xlfn.XLOOKUP(C2,helpdesk_tickets!A2:A537,helpdesk_tickets!H2:H537,"Not Found") -> Not Found
B9: Status | C9: =_xlfn.XLOOKUP(C2,helpdesk_tickets!A2:A537,helpdesk_tickets!J2:J537,"Not Found") -> Not Found
B10: SLA Due Date | C10: =_xlfn.XLOOKUP(C2,helpdesk_tickets!A2:A537,helpdesk_tickets!W2:W537,"Not Found") -> Not Found
B11: Breached SLA | C11: =_xlfn.XLOOKUP(C2,helpdesk_tickets!A2:A537,helpdesk_tickets!X2:X537,"Not Found") -> Not Found

Sheet Summary
B2: Team Assigned | C2: Total Tickets per Team | E2: Type | F2: Total Tickets per Type | H2: Priority | I2: Total Tickets per Priority
B3: SAP Support Team | C3: =COUNTIF(helpdesk_tickets!Q:Q, "SAP Support Team") -> 188 | E3: Incident / Problem | F3: =COUNTIF(helpdesk_tickets!H:H, "Incident / Problem") -> 364 | H3: Emergency | I3: =COUNTIF(helpdesk_tickets!F:F, "Emergency") -> 50
B4: JDE Support Team | C4: =COUNTIF(helpdesk_tickets!Q:Q, "JDE Support Team") -> 246 | E4: Request | F4: =COUNTIF(helpdesk_tickets!H:H, "Request") -> 172 | H4: High | I4: =COUNTIF(helpdesk_tickets!F:F, "High") -> 112
B5: Network Team | C5: =COUNTIF(helpdesk_tickets!Q:Q, "Network Team") -> 36 | H5: Normal | I5: =COUNTIF(helpdesk_tickets!F:F, "Normal") -> 335
B6: AWS Team | C6: =COUNTIF(helpdesk_tickets!Q:Q, "AWS Team") -> 16 | H6: Low | I6: =COUNTIF(helpdesk_tickets!F:F, "Low") -> 39
B7: Help Desk Team | C7: =COUNTIF(helpdesk_tickets!Q:Q, "Help Desk Team") -> 35
B8: Hardware Team | C8: =COUNTIF(helpdesk_tickets!Q:Q, "Hardware Team") -> 2
B9: BPM - ProcessMaker Support Team | C9: =COUNTIF(helpdesk_tickets!Q:Q, "BPM - ProcessMaker Support Team") -> 2
B10: Salesforce Team | C10: =COUNTIF(helpdesk_tickets!Q:Q, "Salesforce Team") -> 7
B11: Workday Team | C11: =COUNTIF(helpdesk_tickets!Q:Q, "Workday Team") -> 4
B16: Current Status | C16: Total Current Status Ticket | E16: Current Status/Answered | F16: Total Open/Answered Tickets | H16: Source | I16: Total Tickets from Source
B17: Closed | C17: =COUNTIF(helpdesk_tickets!J:J, "Closed") -> 462 | E17: Open/Answered | F17: =COUNTIFS(helpdesk_tickets!J:J, "Open", helpdesk_tickets!N:N, "1") -> 28 | H17: Web | I17: =COUNTIF(helpdesk_tickets!I:I, "Web") -> 481
B18: Resolved | C18: =COUNTIF(helpdesk_tickets!J:J, "Resolved") -> 13 | H18: Email | I18: =COUNTIF(helpdesk_tickets!I:I, "Email") -> 28
B19: Open | C19: =COUNTIF(helpdesk_tickets!J:J, "Open") -> 61 | H19: Phone | I19: =COUNTIF(helpdesk_tickets!I:I, "Phone") -> 24
